[
  {
    "gt_one_percent": [
      {
        "_id": "5df9bbc7546f640a3e9960be",
        "52wk_low": 13.79,
        "52wk_high": 31.06,
        "chg": 0.59,
        "chg_pct": 2.82,
        "date": "2019-12-18T05:39:54.881Z",
        "day_high": 21.54,
        "day_low": 21.17,
        "div": 0.75,
        "ex_div": "Jan 14, 2020",
        "last": 21.54,
        "name": "Nabors Industries Ltd. 6% Conv. Pfd. Series A",
        "quoteTime": "Dec 17, 2019 6:30 p.m.",
        "relative_volume": 3.8280000000000003,
        "ticker": "nbr.pra",
        "volume": 166.9,
        "yield": 13.93
      },
      {
        "_id": "5df9bbc7546f640a3e996018",
        "52wk_low": 45.21,
        "52wk_high": 58.41,
        "chg": 1.3794,
        "chg_pct": 2.64,
        "date": "2019-12-18T05:39:47.321Z",
        "day_high": 54.34,
        "day_low": 52.07,
        "div": 0.75,
        "ex_div": "Dec 12, 2019",
        "last": 53.71,
        "name": "Change Healthcare Inc. Un",
        "quoteTime": "Dec 17, 2019 3:37 p.m.",
        "relative_volume": 2.347,
        "ticker": "chngu",
        "volume": 210.5,
        "yield": 5.59
      },
      {
        "_id": "5df9bbc7546f640a3e996004",
        "52wk_low": 23.74,
        "52wk_high": 27.5,
        "chg": 0.64,
        "chg_pct": 2.5,
        "date": "2019-12-18T05:39:47.656Z",
        "day_high": 27.26,
        "day_low": 25.95,
        "div": 0.13,
        "ex_div": "Sep 12, 2019",
        "last": 26.22,
        "name": "Popular Capital Trust II 6.125% Cum. Monthly Income Trust Pfd. Secs.",
        "quoteTime": "Dec 17, 2019 3:55 p.m.",
        "relative_volume": 4.195,
        "ticker": "bpopm",
        "volume": 17.4,
        "yield": 5.84
      },
      {
        "_id": "5df9bbc7546f640a3e996140",
        "52wk_low": 14.37,
        "52wk_high": 24,
        "chg": 0.4501,
        "chg_pct": 2.02,
        "date": "2019-12-18T05:39:53.110Z",
        "day_high": 22.88,
        "day_low": 22.27,
        "div": 0.55,
        "ex_div": "Nov 7, 2019",
        "last": 22.72,
        "name": "Teekay Offshore Partners L.P. 8.875% Cum. Pfd. Series E",
        "quoteTime": "Dec 17, 2019 6:30 p.m.",
        "relative_volume": 0.55,
        "ticker": "too.pre",
        "volume": 14.9,
        "yield": 9.77
      },
      {
        "_id": "5df9bbc7546f640a3e99613f",
        "52wk_low": 14.05,
        "52wk_high": 23.98,
        "chg": 0.39,
        "chg_pct": 1.88,
        "date": "2019-12-18T05:39:48.532Z",
        "day_high": 21.12,
        "day_low": 20.87,
        "div": 0.45,
        "ex_div": "Nov 7, 2019",
        "last": 21.1,
        "name": "Teekay Offshore Partners L. P. 7.25% Cum. Redeem Pfd. Series A",
        "quoteTime": "Dec 17, 2019 6:30 p.m.",
        "relative_volume": 0.2078,
        "ticker": "too.pra",
        "volume": 6.5,
        "yield": 8.59
      },
      {
        "_id": "5df9bbc7546f640a3e99611a",
        "52wk_low": 48.7,
        "52wk_high": 68.29,
        "chg": 0.97,
        "chg_pct": 1.78,
        "date": "2019-12-18T05:39:55.271Z",
        "day_high": 56.86,
        "day_low": 54.54,
        "div": 0.97,
        "ex_div": "Dec 5, 2019",
        "last": 55.5,
        "name": "SLM Corp. Float. Rate Non-Cum. Pfd. Series B",
        "quoteTime": "Dec 17, 2019 3:48 p.m.",
        "relative_volume": 1.229,
        "ticker": "slmbp",
        "volume": 14.4,
        "yield": 7.63
      },
      {
        "_id": "5df9bbc7546f640a3e995ffd",
        "52wk_low": 24.75,
        "52wk_high": 28.55,
        "chg": 0.4,
        "chg_pct": 1.44,
        "date": "2019-12-18T05:39:47.480Z",
        "day_high": 28.25,
        "day_low": 27.57,
        "div": 0.41,
        "ex_div": "Dec 9, 2019",
        "last": 28.24,
        "name": "Brighthouse Financial Inc. Dep. Pfd. (Rep. 1/1000th Share Pfd. Series A)",
        "quoteTime": "Dec 17, 2019 3:59 p.m.",
        "relative_volume": 1.013,
        "ticker": "bhfap",
        "volume": 52.9,
        "yield": 5.84
      },
      {
        "_id": "5df9bbc7546f640a3e995fce",
        "52wk_low": 17.76,
        "52wk_high": 24.05,
        "chg": 0.2997,
        "chg_pct": 1.39,
        "date": "2019-12-18T05:39:47.690Z",
        "day_high": 21.96,
        "day_low": 21.74,
        "div": 0.46,
        "ex_div": "Dec 30, 2019",
        "last": 21.85,
        "name": "Ashford Hospitality Trust Inc. 7.375% Pfd. Series F",
        "quoteTime": "Dec 17, 2019 6:30 p.m.",
        "relative_volume": 0.6168,
        "ticker": "aht.prf",
        "volume": 5.5,
        "yield": 8.44
      },
      {
        "_id": "5df9bbc7546f640a3e995fd5",
        "52wk_low": 25.05,
        "52wk_high": 27.56,
        "chg": 0.34,
        "chg_pct": 1.28,
        "date": "2019-12-18T05:39:52.721Z",
        "day_high": 26.85,
        "day_low": 26.54,
        "div": 0.38,
        "ex_div": "Nov 27, 2019",
        "last": 26.84,
        "name": "Air Lease Corp. 6.15% Fixed-to-Floating Pfd. Series A",
        "quoteTime": "Dec 17, 2019 6:30 p.m.",
        "relative_volume": 1.0490000000000002,
        "ticker": "al.pra",
        "volume": 23.2,
        "yield": 5.73
      },
      {
        "_id": "5df9bbc7546f640a3e99606e",
        "52wk_low": 20.45,
        "52wk_high": 27.57,
        "chg": 0.3249,
        "chg_pct": 1.26,
        "date": "2019-12-18T05:39:55.065Z",
        "day_high": 26.19,
        "day_low": 25.89,
        "div": 0.32,
        "ex_div": "Dec 13, 2019",
        "last": 26.16,
        "name": "First Republic Bank Dep. Pfd. (Rep. 1/40th 5.125% Non-Cum. Perp. Pfd. Series H)",
        "quoteTime": "Dec 17, 2019 6:30 p.m.",
        "relative_volume": 1.198,
        "ticker": "frc.prh",
        "volume": 10.5,
        "yield": 4.9
      },
      {
        "_id": "5df9bbc7546f640a3e9960e8",
        "52wk_low": 21.01,
        "52wk_high": 26.7,
        "chg": 0.32,
        "chg_pct": 1.23,
        "date": "2019-12-18T05:39:53.732Z",
        "day_high": 26.47,
        "day_low": 26.06,
        "div": 0.37,
        "ex_div": "Nov 20, 2019",
        "last": 26.35,
        "name": "PartnerRe Ltd. 5.875% Redeem. Pfd. Series I",
        "quoteTime": "Dec 17, 2019 6:30 p.m.",
        "relative_volume": 1.915,
        "ticker": "pre.pri",
        "volume": 22.7,
        "yield": 5.57
      },
      {
        "_id": "5df9bbc7546f640a3e996155",
        "52wk_low": 66.63,
        "52wk_high": 105.57,
        "chg": 1.177,
        "chg_pct": 1.18,
        "date": "2019-12-18T05:39:54.552Z",
        "day_high": 101,
        "day_low": 99.93,
        "div": 1.81,
        "ex_div": "Jan 14, 2020",
        "last": 100.74,
        "name": "Virtus Investment Partners Inc. 7.25% Conv. Mand. Pfd. Series D",
        "quoteTime": "Dec 17, 2019 3:55 p.m.",
        "relative_volume": 1.358,
        "ticker": "vrtsp",
        "volume": 5.9,
        "yield": 7.2
      },
      {
        "_id": "5df9bbc7546f640a3e996073",
        "52wk_low": 20.86,
        "52wk_high": 28.04,
        "chg": 0.2813,
        "chg_pct": 1.12,
        "date": "2019-12-18T05:39:49.993Z",
        "day_high": 25.34,
        "day_low": 25.21,
        "div": 0.31,
        "ex_div": "Dec 17, 2019",
        "last": 25.3,
        "name": "Gabelli Equity Trust Inc. 5% Cum. Pfd. Series H",
        "quoteTime": "Dec 17, 2019 6:30 p.m.",
        "relative_volume": 0.4278,
        "ticker": "gab.prh",
        "volume": 1.6,
        "yield": 4.94
      },
      {
        "_id": "5df9bbc7546f640a3e996150",
        "52wk_low": 21.84,
        "52wk_high": 30.77,
        "chg": 0.3068,
        "chg_pct": 1.12,
        "date": "2019-12-18T05:39:56.001Z",
        "day_high": 27.71,
        "day_low": 27.44,
        "div": 0.39,
        "ex_div": "Dec 12, 2019",
        "last": 27.69,
        "name": "Valley National Bancorp 6.25% Perp. Pfd. Series A",
        "quoteTime": "Dec 17, 2019 3:47 p.m.",
        "relative_volume": 2.319,
        "ticker": "vlypp",
        "volume": 19,
        "yield": 5.64
      },
      {
        "_id": "5df9bbc7546f640a3e996065",
        "52wk_low": 24.28,
        "52wk_high": 28.5,
        "chg": 0.3,
        "chg_pct": 1.11,
        "date": "2019-12-18T05:39:48.014Z",
        "day_high": 27.3,
        "day_low": 26.55,
        "div": 0.35,
        "ex_div": "Feb 27, 2020",
        "last": 27.3,
        "name": "Entergy Texas Inc. 5.625% First Mtg. Bonds 060164",
        "quoteTime": "Dec 17, 2019 6:30 p.m.",
        "relative_volume": 0.1648,
        "ticker": "ezt",
        "volume": 1.3,
        "yield": 5.15
      },
      {
        "_id": "5df9bbc7546f640a3e99602b",
        "52wk_low": 24.96,
        "52wk_high": 28.25,
        "chg": 0.3,
        "chg_pct": 1.1,
        "date": "2019-12-18T05:39:51.420Z",
        "day_high": 27.73,
        "day_low": 27.4,
        "div": 0.37,
        "ex_div": "Feb 13, 2020",
        "last": 27.65,
        "name": "CMS Energy Corp. 5.875% Jr. Sub. Notes due 2079",
        "quoteTime": "Dec 17, 2019 6:30 p.m.",
        "relative_volume": 0.46090000000000003,
        "ticker": "cmsd",
        "volume": 23.8,
        "yield": 5.31
      },
      {
        "_id": "5df9bbc7546f640a3e99608d",
        "52wk_low": 25.33,
        "52wk_high": 26.64,
        "chg": 0.2807,
        "chg_pct": 1.07,
        "date": "2019-12-18T05:39:52.671Z",
        "day_high": 26.58,
        "day_low": 26.35,
        "div": 0.39,
        "ex_div": "Nov 29, 2019",
        "last": 26.58,
        "name": "HSBC Holdings PLC ADR (Rep 1/4 of a share of 6.2% Non-Cum. Pfd. Series A)",
        "quoteTime": "Dec 17, 2019 6:30 p.m.",
        "relative_volume": 2.416,
        "ticker": "hsbc.pra",
        "volume": 163.4,
        "yield": 5.83
      },
      {
        "_id": "5df9bbc7546f640a3e995ff6",
        "52wk_low": 23.77,
        "52wk_high": 27.4,
        "chg": 0.27,
        "chg_pct": 1.04,
        "date": "2019-12-18T05:39:52.584Z",
        "day_high": 26.28,
        "day_low": 26.09,
        "div": 0.44,
        "ex_div": "Nov 27, 2019",
        "last": 26.28,
        "name": "Banc of California Inc. Dep.Pfd. (Rep. 1/40th Non-Cum. 7% Perp. Pfd. Series E)",
        "quoteTime": "Dec 17, 2019 6:30 p.m.",
        "relative_volume": 1.683,
        "ticker": "banc.pre",
        "volume": 11.3,
        "yield": 6.66
      },
      {
        "_id": "5df9bbc7546f640a3e9960d5",
        "52wk_low": 22.06,
        "52wk_high": 29.95,
        "chg": 0.28,
        "chg_pct": 1.03,
        "date": "2019-12-18T05:39:54.476Z",
        "day_high": 27.69,
        "day_low": 27.2,
        "div": 0.4,
        "ex_div": "Dec 5, 2019",
        "last": 27.42,
        "name": "New York Community Bancorp Inc. Dep Pfd. (Rep. 1/40th Fixed/Floating Rate Pfd. Series A)",
        "quoteTime": "Dec 17, 2019 6:30 p.m.",
        "relative_volume": 1.013,
        "ticker": "nycb.pra",
        "volume": 35.7,
        "yield": 5.81
      }
    ],
    "high_yield": [
      {
        "_id": "5df9bbc7546f640a3e9960be",
        "52wk_low": 13.79,
        "52wk_high": 31.06,
        "chg": 0.59,
        "chg_pct": 2.82,
        "date": "2019-12-18T05:39:54.881Z",
        "day_high": 21.54,
        "day_low": 21.17,
        "div": 0.75,
        "ex_div": "Jan 14, 2020",
        "last": 21.54,
        "name": "Nabors Industries Ltd. 6% Conv. Pfd. Series A",
        "quoteTime": "Dec 17, 2019 6:30 p.m.",
        "relative_volume": 3.8280000000000003,
        "ticker": "nbr.pra",
        "volume": 166.9,
        "yield": 13.93
      },
      {
        "_id": "5df9bbc7546f640a3e996140",
        "52wk_low": 14.37,
        "52wk_high": 24,
        "chg": 0.4501,
        "chg_pct": 2.02,
        "date": "2019-12-18T05:39:53.110Z",
        "day_high": 22.88,
        "day_low": 22.27,
        "div": 0.55,
        "ex_div": "Nov 7, 2019",
        "last": 22.72,
        "name": "Teekay Offshore Partners L.P. 8.875% Cum. Pfd. Series E",
        "quoteTime": "Dec 17, 2019 6:30 p.m.",
        "relative_volume": 0.55,
        "ticker": "too.pre",
        "volume": 14.9,
        "yield": 9.77
      },
      {
        "_id": "5df9bbc7546f640a3e9960df",
        "52wk_low": 14.3,
        "52wk_high": 23.15,
        "chg": -0.0576,
        "chg_pct": -0.31,
        "date": "2019-12-18T05:39:55.991Z",
        "day_high": 18.65,
        "day_low": 18.52,
        "div": 0.45,
        "ex_div": "Nov 29, 2019",
        "last": 18.58,
        "name": "Pennsylvania Real Estate Investment Trust Cum. Redeem. Perp. Pfd. Series C",
        "quoteTime": "Dec 17, 2019 6:30 p.m.",
        "relative_volume": 0.9803000000000001,
        "ticker": "pei.prc",
        "volume": 34.8,
        "yield": 9.69
      },
      {
        "_id": "5df9bbc7546f640a3e9960d1",
        "52wk_low": 19.87,
        "52wk_high": 25.57,
        "chg": 0.03,
        "chg_pct": 0.12,
        "date": "2019-12-18T05:39:54.456Z",
        "day_high": 24.73,
        "day_low": 24.57,
        "div": 0.56,
        "ex_div": "Nov 29, 2019",
        "last": 24.67,
        "name": "NuSTAR Energy L.P. 9% Cum. Redeem. Perp. Pfd. Series C",
        "quoteTime": "Dec 17, 2019 6:30 p.m.",
        "relative_volume": 0.6566,
        "ticker": "ns.prc",
        "volume": 18.4,
        "yield": 9.12
      },
      {
        "_id": "5df9bbc7546f640a3e9960b4",
        "52wk_low": 16.01,
        "52wk_high": 23.89,
        "chg": 0.1445,
        "chg_pct": 0.68,
        "date": "2019-12-18T05:39:48.877Z",
        "day_high": 21.5,
        "day_low": 21.15,
        "div": 0.48,
        "ex_div": "Feb 13, 2020",
        "last": 21.5,
        "name": "Maiden Holdings Ltd. 7.75% Notes 2043",
        "quoteTime": "Dec 17, 2019 6:30 p.m.",
        "relative_volume": 3.362,
        "ticker": "mhnc",
        "volume": 22.6,
        "yield": 9.01
      },
      {
        "_id": "5df9bbc7546f640a3e9960cf",
        "52wk_low": 18.21,
        "52wk_high": 24.83,
        "chg": 0,
        "chg_pct": 0,
        "date": "2019-12-18T05:39:55.553Z",
        "day_high": 23.68,
        "day_low": 23.56,
        "div": 0.53,
        "ex_div": "Nov 29, 2019",
        "last": 23.63,
        "name": "NuSTAR Energy L.P. Cum. Redeem. Perp. Pfd. Series A",
        "quoteTime": "Dec 17, 2019 6:30 p.m.",
        "relative_volume": 1.08,
        "ticker": "ns.pra",
        "volume": 23.4,
        "yield": 8.99
      },
      {
        "_id": "5df9bbc7546f640a3e9960d0",
        "52wk_low": 17.21,
        "52wk_high": 23.12,
        "chg": 0.03,
        "chg_pct": 0.14,
        "date": "2019-12-18T05:39:53.148Z",
        "day_high": 21.48,
        "day_low": 21.26,
        "div": 0.48,
        "ex_div": "Nov 29, 2019",
        "last": 21.35,
        "name": "NuSTAR Energy L.P. 7.625% Cum. Redeem. Pfd. Series B",
        "quoteTime": "Dec 17, 2019 6:30 p.m.",
        "relative_volume": 1.8769999999999998,
        "ticker": "ns.prb",
        "volume": 124,
        "yield": 8.93
      },
      {
        "_id": "5df9bbc7546f640a3e9960b3",
        "52wk_low": 13.19,
        "52wk_high": 19.5,
        "chg": 0.1074,
        "chg_pct": 0.58,
        "date": "2019-12-18T05:39:48.474Z",
        "day_high": 18.7,
        "day_low": 18.52,
        "div": 0.41,
        "ex_div": "Feb 27, 2020",
        "last": 18.61,
        "name": "Maiden Holdings Ltd. 6.625% Notes 2046",
        "quoteTime": "Dec 17, 2019 6:30 p.m.",
        "relative_volume": 1.974,
        "ticker": "mhla",
        "volume": 10.9,
        "yield": 8.9
      },
      {
        "_id": "5df9bbc7546f640a3e9960c5",
        "52wk_low": 19.53,
        "52wk_high": 26.17,
        "chg": 0.1172,
        "chg_pct": 0.46,
        "date": "2019-12-18T05:39:53.396Z",
        "day_high": 25.5,
        "day_low": 25.3,
        "div": 0.56,
        "ex_div": "Sep 30, 2019",
        "last": 25.48,
        "name": "NGL Energy Partners LP Perp. Pfd. Cl B Fixed/Floating",
        "quoteTime": "Dec 17, 2019 6:30 p.m.",
        "relative_volume": 0.1725,
        "ticker": "ngl.prb",
        "volume": 5.6,
        "yield": 8.83
      },
      {
        "_id": "5df9bbc7546f640a3e99607b",
        "52wk_low": 18.16,
        "52wk_high": 24.9,
        "chg": 0.02,
        "chg_pct": 0.08,
        "date": "2019-12-18T05:39:52.805Z",
        "day_high": 24.34,
        "day_low": 24.17,
        "div": 0.53,
        "ex_div": "Dec 6, 2019",
        "last": 24.26,
        "name": "GasLog Partners LP 8.5% Perp. Pfd. Series C",
        "quoteTime": "Dec 17, 2019 6:30 p.m.",
        "relative_volume": 1.5090000000000001,
        "ticker": "glop.prc",
        "volume": 42.1,
        "yield": 8.76
      }
    ],
    "lt_one_percent": [
      {
        "_id": "5df9bbc7546f640a3e996133",
        "52wk_low": 21.86,
        "52wk_high": 27.56,
        "chg": -0.33,
        "chg_pct": -1.23,
        "date": "2019-12-18T05:39:48.307Z",
        "day_high": 26.9,
        "day_low": 26.55,
        "div": 0.33,
        "ex_div": "Oct 16, 2019",
        "last": 26.56,
        "name": "AT&T Inc. 5.35% Global Notes due 2066",
        "quoteTime": "Dec 17, 2019 6:30 p.m.",
        "relative_volume": 1.284,
        "ticker": "tbb",
        "volume": 149.6,
        "yield": 5.03
      },
      {
        "_id": "5df9bbc7546f640a3e99605f",
        "52wk_low": 25.01,
        "52wk_high": 29.88,
        "chg": -0.335,
        "chg_pct": -1.15,
        "date": "2019-12-18T05:39:52.092Z",
        "day_high": 28.9,
        "day_low": 28.9,
        "div": 0.41,
        "ex_div": "Oct 30, 2019",
        "last": 28.9,
        "name": "Equity Commonwealth 6.5% Cum. Conv. Pfd. Series D",
        "quoteTime": "Dec 17, 2019 6:30 p.m.",
        "relative_volume": 0.1115,
        "ticker": "eqc.prd",
        "volume": 1,
        "yield": 5.62
      },
      {
        "_id": "5df9bbc7546f640a3e996005",
        "52wk_low": 24.87,
        "52wk_high": 31.97,
        "chg": -0.2795,
        "chg_pct": -1.07,
        "date": "2019-12-18T05:39:47.660Z",
        "day_high": 26.33,
        "day_low": 25.95,
        "div": 0.14,
        "ex_div": "Dec 12, 2019",
        "last": 25.95,
        "name": "Popular Inc. 6.375% Cum. Monthly Income Trust Pfd. Securities",
        "quoteTime": "Dec 17, 2019 3:25 p.m.",
        "relative_volume": 0.348,
        "ticker": "bpopn",
        "volume": 2.3,
        "yield": 6.45
      },
      {
        "_id": "5df9bbc7546f640a3e99605b",
        "52wk_low": 76.97,
        "52wk_high": 111.08,
        "chg": -1.1254,
        "chg_pct": -1.05,
        "date": "2019-12-18T05:39:49.891Z",
        "day_high": 106.6,
        "day_low": 105.73,
        "div": 1.88,
        "ex_div": "Dec 30, 2019",
        "last": 105.73,
        "name": "Energizer Holdings Inc. 7.5% Pfd. Series A",
        "quoteTime": "Dec 17, 2019 6:30 p.m.",
        "relative_volume": 0.08990999999999999,
        "ticker": "enr.pra",
        "volume": 1.9,
        "yield": 7.09
      },
      {
        "_id": "5df9bbc7546f640a3e99611d",
        "52wk_low": 22.58,
        "52wk_high": 27.98,
        "chg": -0.27,
        "chg_pct": -1,
        "date": "2019-12-18T05:39:56.012Z",
        "day_high": 27.14,
        "day_low": 26.65,
        "div": 0.39,
        "ex_div": "Dec 12, 2019",
        "last": 26.65,
        "name": "Synovus Financial Corp. Fixed-to-Floating Rate Non-Cum. Perp. Pfd. Series D",
        "quoteTime": "Dec 17, 2019 6:30 p.m.",
        "relative_volume": 1.781,
        "ticker": "snv.prd",
        "volume": 26.7,
        "yield": 5.91
      }
    ],
    "rel_vol": [
      {
        "_id": "5df9bbc7546f640a3e996085",
        "52wk_low": 24.71,
        "52wk_high": 28.27,
        "chg": 0.1513,
        "chg_pct": 0.58,
        "date": "2019-12-18T05:39:49.895Z",
        "day_high": 26.48,
        "day_low": 26.14,
        "div": 0.35,
        "ex_div": "Dec 17, 2019",
        "last": 26.21,
        "name": "Gabelli Utility Trust 5.625% Cum. Pfd. Series A",
        "quoteTime": "Dec 17, 2019 6:30 p.m.",
        "relative_volume": 4.647,
        "ticker": "gut.pra",
        "volume": 4.2,
        "yield": 5.36
      },
      {
        "_id": "5df9bbc7546f640a3e996004",
        "52wk_low": 23.74,
        "52wk_high": 27.5,
        "chg": 0.64,
        "chg_pct": 2.5,
        "date": "2019-12-18T05:39:47.656Z",
        "day_high": 27.26,
        "day_low": 25.95,
        "div": 0.13,
        "ex_div": "Sep 12, 2019",
        "last": 26.22,
        "name": "Popular Capital Trust II 6.125% Cum. Monthly Income Trust Pfd. Secs.",
        "quoteTime": "Dec 17, 2019 3:55 p.m.",
        "relative_volume": 4.195,
        "ticker": "bpopm",
        "volume": 17.4,
        "yield": 5.84
      },
      {
        "_id": "5df9bbc7546f640a3e995fd0",
        "52wk_low": 18.05,
        "52wk_high": 23.77,
        "chg": 0.01,
        "chg_pct": 0.05,
        "date": "2019-12-18T05:39:47.452Z",
        "day_high": 22.04,
        "day_low": 21.89,
        "div": 0.47,
        "ex_div": "Dec 30, 2019",
        "last": 21.99,
        "name": "Ashford Hospitality Trust 7.5% Cum. Pfd. Series H",
        "quoteTime": "Dec 17, 2019 6:30 p.m.",
        "relative_volume": 3.865,
        "ticker": "aht.prh",
        "volume": 24.9,
        "yield": 8.53
      },
      {
        "_id": "5df9bbc7546f640a3e9960be",
        "52wk_low": 13.79,
        "52wk_high": 31.06,
        "chg": 0.59,
        "chg_pct": 2.82,
        "date": "2019-12-18T05:39:54.881Z",
        "day_high": 21.54,
        "day_low": 21.17,
        "div": 0.75,
        "ex_div": "Jan 14, 2020",
        "last": 21.54,
        "name": "Nabors Industries Ltd. 6% Conv. Pfd. Series A",
        "quoteTime": "Dec 17, 2019 6:30 p.m.",
        "relative_volume": 3.8280000000000003,
        "ticker": "nbr.pra",
        "volume": 166.9,
        "yield": 13.93
      },
      {
        "_id": "5df9bbc7546f640a3e996153",
        "52wk_low": 19.5,
        "52wk_high": 26.72,
        "chg": -0.0348,
        "chg_pct": -0.14,
        "date": "2019-12-18T05:39:55.965Z",
        "day_high": 25.75,
        "day_low": 25.6,
        "div": 0.33,
        "ex_div": "Dec 13, 2019",
        "last": 25.74,
        "name": "Vornado Realty Trust 5.25% Cum. Redeem. Perp. Pfd. Series M",
        "quoteTime": "Dec 17, 2019 6:30 p.m.",
        "relative_volume": 3.802,
        "ticker": "vno.prm",
        "volume": 105.8,
        "yield": 5.1
      },
      {
        "_id": "5df9bbc7546f640a3e996116",
        "52wk_low": 22.58,
        "52wk_high": 28,
        "chg": 0.0186,
        "chg_pct": 0.07,
        "date": "2019-12-18T05:39:55.616Z",
        "day_high": 26.23,
        "day_low": 26.1,
        "div": 0.4,
        "ex_div": "Dec 30, 2019",
        "last": 26.23,
        "name": "Sunstone Hotel Investors Inc. 6.45% Cum. Pfd. Series F",
        "quoteTime": "Dec 16, 2019 6:30 p.m.",
        "relative_volume": 3.377,
        "ticker": "sho.prf",
        "volume": 11.6,
        "yield": 6.15
      },
      {
        "_id": "5df9bbc7546f640a3e9960b4",
        "52wk_low": 16.01,
        "52wk_high": 23.89,
        "chg": 0.1445,
        "chg_pct": 0.68,
        "date": "2019-12-18T05:39:48.877Z",
        "day_high": 21.5,
        "day_low": 21.15,
        "div": 0.48,
        "ex_div": "Feb 13, 2020",
        "last": 21.5,
        "name": "Maiden Holdings Ltd. 7.75% Notes 2043",
        "quoteTime": "Dec 17, 2019 6:30 p.m.",
        "relative_volume": 3.362,
        "ticker": "mhnc",
        "volume": 22.6,
        "yield": 9.01
      },
      {
        "_id": "5df9bbc7546f640a3e996010",
        "52wk_low": 4.01,
        "52wk_high": 14.97,
        "chg": 0.14,
        "chg_pct": 2.81,
        "date": "2019-12-18T05:39:47.801Z",
        "day_high": 5.2,
        "day_low": 4.9,
        "div": 0.46,
        "ex_div": "Sep 13, 2019",
        "last": 5.13,
        "name": "CBL & Associates Properties Inc. Dep. Pfd. (Rep. 1/10th fraction interest of a share of 7.375% Cum. Pfd. Series D)",
        "quoteTime": "Dec 17, 2019 6:30 p.m.",
        "relative_volume": 3.195,
        "ticker": "cbl.prd",
        "volume": 694.2,
        "yield": 35.95
      },
      {
        "_id": "5df9bbc7546f640a3e9960f9",
        "52wk_low": 20.07,
        "52wk_high": 27.03,
        "chg": 0.02,
        "chg_pct": 0.08,
        "date": "2019-12-18T05:39:56.005Z",
        "day_high": 25.47,
        "day_low": 25.3,
        "div": 0.32,
        "ex_div": "Dec 12, 2019",
        "last": 25.4,
        "name": "PS Business Parks Inc. Dep. Pfd. (Rep. 1/1000th Cum. Perp. Pfd. Series Y)",
        "quoteTime": "Dec 17, 2019 6:30 p.m.",
        "relative_volume": 3.069,
        "ticker": "psb.pry",
        "volume": 90.6,
        "yield": 5.12
      },
      {
        "_id": "5df9bbc7546f640a3e99609e",
        "52wk_low": 24.5,
        "52wk_high": 30.91,
        "chg": 0.02,
        "chg_pct": 0.07,
        "date": "2019-12-18T05:39:52.992Z",
        "day_high": 28.8,
        "day_low": 28.45,
        "div": 0.38,
        "ex_div": "Nov 29, 2019",
        "last": 28.55,
        "name": "KeyCorp Dep. Pfd. (Rep. 1/40th Non-Cum. Perp. Pfd. Series E)",
        "quoteTime": "Dec 17, 2019 6:30 p.m.",
        "relative_volume": 3.016,
        "ticker": "key.pri",
        "volume": 104.3,
        "yield": 5.36
      },
      {
        "_id": "5df9bbc7546f640a3e995fe7",
        "52wk_low": 21.45,
        "52wk_high": 25.25,
        "chg": -0.01,
        "chg_pct": -0.04,
        "date": "2019-12-18T05:39:47.098Z",
        "day_high": 25.1,
        "day_low": 25.02,
        "div": 0.16,
        "ex_div": "Dec 12, 2019",
        "last": 25.07,
        "name": "Armour Residential REIT Inc. 7.875% Cum. Redeem. Pfd. Series B",
        "quoteTime": "Dec 17, 2019 6:30 p.m.",
        "relative_volume": 2.983,
        "ticker": "arr.prb",
        "volume": 85,
        "yield": 7.86
      },
      {
        "_id": "5df9bbc7546f640a3e9960a7",
        "52wk_low": 19.43,
        "52wk_high": 25.55,
        "chg": 0,
        "chg_pct": 0.02,
        "date": "2019-12-18T05:39:51.853Z",
        "day_high": 25.11,
        "day_low": 25.04,
        "div": 0.17,
        "ex_div": "Dec 12, 2019",
        "last": 25.07,
        "name": "Ladenburg Thalmann Financial Services Inc. 8% Cum. Redeem. Pfd. Series A",
        "quoteTime": "Dec 17, 2019 8:00 p.m.",
        "relative_volume": 2.98,
        "ticker": "lts.pra",
        "volume": 170.2,
        "yield": 7.98
      },
      {
        "_id": "5df9bbc7546f640a3e99608a",
        "52wk_low": 25.04,
        "52wk_high": 29.39,
        "chg": 0.2,
        "chg_pct": 0.73,
        "date": "2019-12-18T05:39:47.765Z",
        "day_high": 27.51,
        "day_low": 27.21,
        "div": 0.38,
        "ex_div": "Jan 30, 2020",
        "last": 27.47,
        "name": "Hartford Financial Services Group Inc. Dep. Pfd. (Rep. 1/1000 Share 6% Pfd. Series G)",
        "quoteTime": "Dec 17, 2019 6:30 p.m.",
        "relative_volume": 2.964,
        "ticker": "hig.prg",
        "volume": 131.3,
        "yield": 5.46
      },
      {
        "_id": "5df9bbc7546f640a3e996132",
        "52wk_low": 22.51,
        "52wk_high": 25.74,
        "chg": 0.05,
        "chg_pct": 0.2,
        "date": "2019-12-18T05:39:50.186Z",
        "day_high": 25.41,
        "day_low": 25.2,
        "div": 0.5,
        "ex_div": "Mar 31, 2020",
        "last": 25.25,
        "name": "TravelCenters of America Inc. 8% Sr. Notes 101530",
        "quoteTime": "Dec 17, 2019 3:47 p.m.",
        "relative_volume": 2.8369999999999997,
        "ticker": "tannz",
        "volume": 20.8,
        "yield": 7.92
      },
      {
        "_id": "5df9bbc7546f640a3e995ff7",
        "52wk_low": 21.27,
        "52wk_high": 25.98,
        "chg": 0.224,
        "chg_pct": 0.88,
        "date": "2019-12-18T05:39:51.738Z",
        "day_high": 25.59,
        "day_low": 25.36,
        "div": 0.32,
        "ex_div": "Nov 7, 2019",
        "last": 25.56,
        "name": "BB&T Corp. Dep. Pfd. (Rep. 1/1000th Perp. Pfd. Series F)",
        "quoteTime": "Dec 17, 2019 6:30 p.m.",
        "relative_volume": 2.615,
        "ticker": "bbt.prf",
        "volume": 62.6,
        "yield": 5.09
      },
      {
        "_id": "5df9bbc7546f640a3e996074",
        "52wk_low": 24.11,
        "52wk_high": 27.29,
        "chg": 0.1406,
        "chg_pct": 0.54,
        "date": "2019-12-18T05:39:52.793Z",
        "day_high": 26.09,
        "day_low": 25.9,
        "div": 0.34,
        "ex_div": "Dec 17, 2019",
        "last": 26,
        "name": "Gabelli Equity Trust Inc. 5.45% Cum. Pfd. Series J",
        "quoteTime": "Dec 17, 2019 6:30 p.m.",
        "relative_volume": 2.591,
        "ticker": "gab.prj",
        "volume": 7,
        "yield": 5.24
      },
      {
        "_id": "5df9bbc7546f640a3e99606b",
        "52wk_low": 17.81,
        "52wk_high": 25.35,
        "chg": -0.1216,
        "chg_pct": -0.49,
        "date": "2019-12-18T05:39:52.553Z",
        "day_high": 24.65,
        "day_low": 24.43,
        "div": 0.38,
        "ex_div": "Dec 12, 2019",
        "last": 24.5,
        "name": "Farmland Partners Inc. 6% Pfd. Series B",
        "quoteTime": "Dec 17, 2019 6:30 p.m.",
        "relative_volume": 2.57,
        "ticker": "fpi.prb",
        "volume": 39.3,
        "yield": 6.12
      },
      {
        "_id": "5df9bbc7546f640a3e99600b",
        "52wk_low": 22.05,
        "52wk_high": 25.83,
        "chg": -0.0193,
        "chg_pct": -0.08,
        "date": "2019-12-18T05:39:47.873Z",
        "day_high": 25.54,
        "day_low": 25.3,
        "div": 0.33,
        "ex_div": "Oct 31, 2019",
        "last": 25.5,
        "name": "Boston Properties Inc. Dep. (Rep. 1/100th 5.25% Cum. Redeem. Pfd. Series B)",
        "quoteTime": "Dec 17, 2019 6:30 p.m.",
        "relative_volume": 2.4659999999999997,
        "ticker": "bxp.prb",
        "volume": 31.6,
        "yield": 5.15
      },
      {
        "_id": "5df9bbc7546f640a3e99608d",
        "52wk_low": 25.33,
        "52wk_high": 26.64,
        "chg": 0.2807,
        "chg_pct": 1.07,
        "date": "2019-12-18T05:39:52.671Z",
        "day_high": 26.58,
        "day_low": 26.35,
        "div": 0.39,
        "ex_div": "Nov 29, 2019",
        "last": 26.58,
        "name": "HSBC Holdings PLC ADR (Rep 1/4 of a share of 6.2% Non-Cum. Pfd. Series A)",
        "quoteTime": "Dec 17, 2019 6:30 p.m.",
        "relative_volume": 2.416,
        "ticker": "hsbc.pra",
        "volume": 163.4,
        "yield": 5.83
      },
      {
        "_id": "5df9bbc7546f640a3e996111",
        "52wk_low": 24.58,
        "52wk_high": 27.37,
        "chg": 0.03,
        "chg_pct": 0.12,
        "date": "2019-12-18T05:39:55.168Z",
        "day_high": 26.06,
        "day_low": 25.93,
        "div": 0.38,
        "ex_div": "Nov 14, 2019",
        "last": 26.01,
        "name": "Charles Schwab Corp. Dep. Pfd. (Rep. 1/40th 6% Non-Cum. Pfd. Series C)",
        "quoteTime": "Dec 17, 2019 6:30 p.m.",
        "relative_volume": 2.385,
        "ticker": "schw.prc",
        "volume": 110.6,
        "yield": 5.77
      },
      {
        "_id": "5df9bbc7546f640a3e996018",
        "52wk_low": 45.21,
        "52wk_high": 58.41,
        "chg": 1.3794,
        "chg_pct": 2.64,
        "date": "2019-12-18T05:39:47.321Z",
        "day_high": 54.34,
        "day_low": 52.07,
        "div": 0.75,
        "ex_div": "Dec 12, 2019",
        "last": 53.71,
        "name": "Change Healthcare Inc. Un",
        "quoteTime": "Dec 17, 2019 3:37 p.m.",
        "relative_volume": 2.347,
        "ticker": "chngu",
        "volume": 210.5,
        "yield": 5.59
      },
      {
        "_id": "5df9bbc7546f640a3e996150",
        "52wk_low": 21.84,
        "52wk_high": 30.77,
        "chg": 0.3068,
        "chg_pct": 1.12,
        "date": "2019-12-18T05:39:56.001Z",
        "day_high": 27.71,
        "day_low": 27.44,
        "div": 0.39,
        "ex_div": "Dec 12, 2019",
        "last": 27.69,
        "name": "Valley National Bancorp 6.25% Perp. Pfd. Series A",
        "quoteTime": "Dec 17, 2019 3:47 p.m.",
        "relative_volume": 2.319,
        "ticker": "vlypp",
        "volume": 19,
        "yield": 5.64
      },
      {
        "_id": "5df9bbc7546f640a3e996104",
        "52wk_low": 23.55,
        "52wk_high": 27.66,
        "chg": -0.05,
        "chg_pct": -0.19,
        "date": "2019-12-18T05:39:48.827Z",
        "day_high": 25.97,
        "day_low": 25.88,
        "div": 0.46,
        "ex_div": "Oct 14, 2020",
        "last": 25.89,
        "name": "B. Riley Financial Inc. 7.375% Sr. Notes 053123",
        "quoteTime": "Dec 17, 2019 3:49 p.m.",
        "relative_volume": 2.306,
        "ticker": "rilyh",
        "volume": 24.2,
        "yield": 7.12
      },
      {
        "_id": "5df9bbc7546f640a3e995fe5",
        "52wk_low": 25.35,
        "52wk_high": 28.24,
        "chg": 0.05,
        "chg_pct": 0.19,
        "date": "2019-12-18T05:39:47.317Z",
        "day_high": 27.01,
        "day_low": 26.89,
        "div": 0.39,
        "ex_div": "Mar 12, 2020",
        "last": 27,
        "name": "Algonquin Power & Utilities Corp. 6.2% Fixed-to-Floating Sub. Notes 070179",
        "quoteTime": "Dec 17, 2019 6:30 p.m.",
        "relative_volume": 2.27,
        "ticker": "aqnb",
        "volume": 59.1,
        "yield": 5.74
      },
      {
        "_id": "5df9bbc7546f640a3e995fd7",
        "52wk_low": 23.3,
        "52wk_high": 27.35,
        "chg": 0.0142,
        "chg_pct": 0.05,
        "date": "2019-12-18T05:39:49.603Z",
        "day_high": 26.54,
        "day_low": 26.43,
        "div": 0.32,
        "ex_div": "Mar 31, 2020",
        "last": 26.51,
        "name": "Allstate Corp. 5.1% Fixed-To-Floating Rate Sub. Deb. due 2053",
        "quoteTime": "Dec 17, 2019 6:30 p.m.",
        "relative_volume": 2.176,
        "ticker": "all.prb",
        "volume": 73.2,
        "yield": 4.81
      },
      {
        "_id": "5df9bbc7546f640a3e9960c7",
        "52wk_low": 24.85,
        "52wk_high": 28.45,
        "chg": 0.17,
        "chg_pct": 0.63,
        "date": "2019-12-18T05:39:53.175Z",
        "day_high": 27.32,
        "day_low": 27.12,
        "div": 0.41,
        "ex_div": "Aug 22, 2019",
        "last": 27.31,
        "name": "NiSource Inc. Dep. Pfd. (Rep. 1/1000th Share Perp. Pfd. Series B)",
        "quoteTime": "Dec 17, 2019 6:30 p.m.",
        "relative_volume": 2.158,
        "ticker": "ni.prb",
        "volume": 68.6,
        "yield": 5.95
      },
      {
        "_id": "5df9bbc7546f640a3e9960f4",
        "52wk_low": 21.33,
        "52wk_high": 25.73,
        "chg": -0.0088,
        "chg_pct": -0.03,
        "date": "2019-12-18T05:39:56.073Z",
        "day_high": 25.28,
        "day_low": 25.21,
        "div": 0.32,
        "ex_div": "Dec 12, 2019",
        "last": 25.21,
        "name": "Public Storage Dep. Pfd. (Rep. 1/1000th Pfd. SBI Series W)",
        "quoteTime": "Dec 17, 2019 6:30 p.m.",
        "relative_volume": 2.135,
        "ticker": "psa.prw",
        "volume": 66.3,
        "yield": 5.16
      },
      {
        "_id": "5df9bbc7546f640a3e995fc3",
        "52wk_low": 24.18,
        "52wk_high": 25.95,
        "chg": -0.04,
        "chg_pct": -0.16,
        "date": "2019-12-18T05:39:47.926Z",
        "day_high": 25.28,
        "day_low": 25.15,
        "div": 0.47,
        "ex_div": "Oct 3, 2019",
        "last": 25.21,
        "name": "American Finance Trust Inc. 7.5% Pfd. Series A",
        "quoteTime": "Dec 17, 2019 4:00 p.m.",
        "relative_volume": 2.122,
        "ticker": "afinp",
        "volume": 165.9,
        "yield": 7.44
      },
      {
        "_id": "5df9bbc7546f640a3e9960a3",
        "52wk_low": 24.6,
        "52wk_high": 28.52,
        "chg": 0.1027,
        "chg_pct": 0.39,
        "date": "2019-12-18T05:39:53.167Z",
        "day_high": 26.69,
        "day_low": 26.56,
        "div": 0.42,
        "ex_div": "Nov 27, 2019",
        "last": 26.65,
        "name": "KKR & Co. Inc. 6.75% Perp. Pfd. Series A",
        "quoteTime": "Dec 17, 2019 6:30 p.m.",
        "relative_volume": 2.096,
        "ticker": "kkr.pra",
        "volume": 50,
        "yield": 6.33
      },
      {
        "_id": "5df9bbc7546f640a3e99604d",
        "52wk_low": 25.1,
        "52wk_high": 28.56,
        "chg": -0.05,
        "chg_pct": -0.18,
        "date": "2019-12-18T05:39:46.947Z",
        "day_high": 27.74,
        "day_low": 27.64,
        "div": 0.36,
        "ex_div": "Nov 14, 2019",
        "last": 27.65,
        "name": "Duke Energy Corp. Dep. Pfd. (Rep. 1/1000th 5.75% Pfd. Series A)",
        "quoteTime": "Dec 17, 2019 6:30 p.m.",
        "relative_volume": 2.055,
        "ticker": "duk.pra",
        "volume": 205.8,
        "yield": 5.2
      },
      {
        "_id": "5df9bbc7546f640a3e996131",
        "52wk_low": 22.6,
        "52wk_high": 26.87,
        "chg": 0.2196,
        "chg_pct": 0.88,
        "date": "2019-12-18T05:39:50.474Z",
        "day_high": 25.2,
        "day_low": 25,
        "div": 0.5,
        "ex_div": "May 14, 2020",
        "last": 25.16,
        "name": "TravelCenters of America Inc. 8% Sr. Notes 121529",
        "quoteTime": "Dec 17, 2019 3:45 p.m.",
        "relative_volume": 2.0269999999999997,
        "ticker": "tannl",
        "volume": 16.9,
        "yield": 7.95
      }
    ]
  }
]